opac_mixer/__init__.py
opac_mixer/emulator.py
opac_mixer/mix.py
opac_mixer/read.py
opac_mixer/patches/__init__.py
opac_mixer/patches/prt.py
opac_mixer/utils/__init__.py
opac_mixer/utils/callbacks.py
opac_mixer/utils/interp.py
opac_mixer/utils/models.py
opac_mixer/utils/scalings.py
opac_mixer-1.0.1.dist-info/LICENSE
opac_mixer-1.0.1.dist-info/METADATA
opac_mixer-1.0.1.dist-info/WHEEL
opac_mixer-1.0.1.dist-info/top_level.txt
opac_mixer-1.0.1.dist-info/RECORD
