Metadata-Version: 2.1
Name: opac-mixer
Version: 1.0.1
Summary: opacity mixing - accelerated
Home-page: https://opacmixer.readthedocs.io/en/latest/
Author: Aaron David Schneider
Author-email: aaron.schneider@nbi.ku.dk
License: MIT
License-File: LICENSE
Requires-Dist: scikit-learn
Requires-Dist: numba
Requires-Dist: scipy
Requires-Dist: numpy
Requires-Dist: matplotlib
Requires-Dist: tqdm
Requires-Dist: h5py
Requires-Dist: tensorflow
Requires-Dist: MITgcmutils
